{
    "id": "5c2f4f47f0f0b16f80cb98a7",
    "教育": [
        {
            "学校": [
                "3",
                [
                    "南京农业大学"
                ]
            ],
            "学历": [
                "3",
                [
                    "硕士"
                ]
            ],
            "专业": [
                "1",
                [
                    "园艺"
                ]
            ]
        },
        {
            "学校": [
                "3",
                [
                    "海南大学"
                ]
            ],
            "学历": [
                "3",
                [
                    "本科"
                ]
            ],
            "专业": [
                "1",
                [
                    "风景园林"
                ]
            ]
        }
    ],
    "经验": {
        "工作经验": [
            {
                "公司名": [
                    "3",
                    [
                        "无锡尚德电力"
                    ]
                ],
                "所在城市": [
                    "4",
                    []
                ],
                "业务": [
                    "1",
                    [
                        "商务合作模式",
                        "渠道网络规模"
                    ]
                ],
                "产品": [
                    "1",
                    []
                ],
                "职位": [
                    "1",
                    [
                        "渠道",
                        "分销经理"
                    ]
                ],
                "年限": [
                    "2",
                    [
                        0.7
                    ]
                ],
                "行业": [
                    "1",
                    [
                        "电气",
                        "电力",
                        "水利"
                    ]
                ]
            },
            {
                "公司名": [
                    "3",
                    [
                        "尼泊尔"
                    ]
                ],
                "所在城市": [
                    "4",
                    []
                ],
                "业务": [
                    "1",
                    []
                ],
                "产品": [
                    "1",
                    []
                ],
                "职位": [
                    "1",
                    [
                        "志愿者",
                        "社会工作者"
                    ]
                ],
                "年限": [
                    "2",
                    [
                        0.1
                    ]
                ],
                "行业": [
                    "1",
                    []
                ]
            },
            {
                "公司名": [
                    "3",
                    [
                        "拉萨青旅"
                    ]
                ],
                "所在城市": [
                    "4",
                    []
                ],
                "业务": [
                    "1",
                    []
                ],
                "产品": [
                    "1",
                    []
                ],
                "职位": [
                    "1",
                    [
                        "志愿者",
                        "社会工作者"
                    ]
                ],
                "年限": [
                    "2",
                    [
                        0.1
                    ]
                ],
                "行业": [
                    "1",
                    []
                ]
            },
            {
                "公司名": [
                    "3",
                    [
                        "国际学术研讨会"
                    ]
                ],
                "所在城市": [
                    "4",
                    []
                ],
                "业务": [
                    "1",
                    []
                ],
                "产品": [
                    "1",
                    []
                ],
                "职位": [
                    "1",
                    [
                        "志愿者",
                        "社会工作者"
                    ]
                ],
                "年限": [
                    "2",
                    [
                        0.0
                    ]
                ],
                "行业": [
                    "1",
                    []
                ]
            },
            {
                "公司名": [
                    "3",
                    [
                        "新疆（伊犁和喀什）青旅义工"
                    ]
                ],
                "所在城市": [
                    "4",
                    []
                ],
                "业务": [
                    "1",
                    []
                ],
                "产品": [
                    "1",
                    []
                ],
                "职位": [
                    "1",
                    [
                        "志愿者",
                        "社会工作者"
                    ]
                ],
                "年限": [
                    "2",
                    [
                        0.1
                    ]
                ],
                "行业": [
                    "1",
                    []
                ]
            },
            {
                "公司名": [
                    "3",
                    [
                        "越南（沙巴和老街）"
                    ]
                ],
                "所在城市": [
                    "4",
                    []
                ],
                "业务": [
                    "1",
                    []
                ],
                "产品": [
                    "1",
                    []
                ],
                "职位": [
                    "1",
                    [
                        "志愿者",
                        "社会工作者"
                    ]
                ],
                "年限": [
                    "2",
                    [
                        0.1
                    ]
                ],
                "行业": [
                    "1",
                    []
                ]
            },
            {
                "公司名": [
                    "3",
                    [
                        "南京农业大学校研会权益部部长"
                    ]
                ],
                "所在城市": [
                    "4",
                    []
                ],
                "业务": [
                    "1",
                    []
                ],
                "产品": [
                    "1",
                    []
                ],
                "职位": [
                    "1",
                    [
                        "其他"
                    ]
                ],
                "年限": [
                    "2",
                    [
                        1.6
                    ]
                ],
                "行业": [
                    "1",
                    []
                ]
            },
            {
                "公司名": [
                    "3",
                    [
                        "斯里兰卡海龟保育志愿者"
                    ]
                ],
                "所在城市": [
                    "4",
                    []
                ],
                "业务": [
                    "1",
                    []
                ],
                "产品": [
                    "1",
                    []
                ],
                "职位": [
                    "1",
                    [
                        "志愿者",
                        "社会工作者"
                    ]
                ],
                "年限": [
                    "2",
                    [
                        0.0
                    ]
                ],
                "行业": [
                    "1",
                    []
                ]
            },
            {
                "公司名": [
                    "3",
                    [
                        "缅甸的玉石生意"
                    ]
                ],
                "所在城市": [
                    "4",
                    []
                ],
                "业务": [
                    "1",
                    []
                ],
                "产品": [
                    "1",
                    []
                ],
                "职位": [
                    "1",
                    [
                        "志愿者",
                        "社会工作者"
                    ]
                ],
                "年限": [
                    "2",
                    [
                        0.1
                    ]
                ],
                "行业": [
                    "1",
                    []
                ]
            },
            {
                "公司名": [
                    "3",
                    [
                        "环海南岛实训"
                    ]
                ],
                "所在城市": [
                    "4",
                    []
                ],
                "业务": [
                    "1",
                    [
                        "海南岛实训",
                        "五星酒店文华东方",
                        "绿化设计"
                    ]
                ],
                "产品": [
                    "1",
                    []
                ],
                "职位": [
                    "1",
                    [
                        "志愿者",
                        "社会工作者"
                    ]
                ],
                "年限": [
                    "2",
                    [
                        0.1
                    ]
                ],
                "行业": [
                    "1",
                    []
                ]
            },
            {
                "公司名": [
                    "3",
                    [
                        "骑行川藏线318"
                    ]
                ],
                "所在城市": [
                    "4",
                    []
                ],
                "业务": [
                    "1",
                    []
                ],
                "产品": [
                    "1",
                    []
                ],
                "职位": [
                    "1",
                    [
                        "其他"
                    ]
                ],
                "年限": [
                    "2",
                    [
                        0.1
                    ]
                ],
                "行业": [
                    "1",
                    []
                ]
            },
            {
                "公司名": [
                    "3",
                    [
                        "桂林写生实训"
                    ]
                ],
                "所在城市": [
                    "4",
                    []
                ],
                "业务": [
                    "1",
                    []
                ],
                "产品": [
                    "1",
                    []
                ],
                "职位": [
                    "1",
                    [
                        "其他"
                    ]
                ],
                "年限": [
                    "2",
                    [
                        0.1
                    ]
                ],
                "行业": [
                    "1",
                    []
                ]
            },
            {
                "公司名": [
                    "3",
                    [
                        "海口市苍鹰小学"
                    ]
                ],
                "所在城市": [
                    "4",
                    []
                ],
                "业务": [
                    "1",
                    []
                ],
                "产品": [
                    "1",
                    []
                ],
                "职位": [
                    "1",
                    [
                        "志愿者",
                        "社会工作者"
                    ]
                ],
                "年限": [
                    "2",
                    [
                        1.8
                    ]
                ],
                "行业": [
                    "1",
                    []
                ]
            },
            {
                "公司名": [
                    "3",
                    [
                        "海南大学台球协会策划部部长"
                    ]
                ],
                "所在城市": [
                    "4",
                    []
                ],
                "业务": [
                    "1",
                    [
                        "策划",
                        "前期策划"
                    ]
                ],
                "产品": [
                    "1",
                    []
                ],
                "职位": [
                    "1",
                    [
                        "志愿者",
                        "社会工作者"
                    ]
                ],
                "年限": [
                    "2",
                    [
                        1.8
                    ]
                ],
                "行业": [
                    "1",
                    []
                ]
            }
        ],
        "项目经验": [
            {
                "公司名": [
                    "3",
                    []
                ],
                "所在城市": [
                    "4",
                    []
                ],
                "业务": [
                    "1",
                    [
                        "渠道网络规模"
                    ]
                ],
                "产品": [
                    "1",
                    []
                ],
                "职位": [
                    "1",
                    []
                ],
                "年限": [
                    "2",
                    [
                        0.7
                    ]
                ],
                "行业": [
                    "1",
                    []
                ]
            }
        ],
        "其他经验": {
            "公司名": [
                "3",
                []
            ],
            "所在城市": [
                "4",
                []
            ],
            "业务": [
                "1",
                [
                    "海南大学台球协会",
                    "间台球",
                    "前期策划到开展到最后"
                ]
            ],
            "产品": [
                "1",
                []
            ],
            "职位": [
                "1",
                []
            ],
            "年限": [
                "2",
                []
            ],
            "行业": [
                "1",
                []
            ]
        }
    },
    "技能": [
        "1",
        [
            "早餐文化节",
            "英语",
            "园林规划",
            "桂林写生",
            "面向学生授予知识",
            "lsquo",
            "rsquo",
            "英语口语无障碍",
            "lsquo",
            "rsquo"
        ]
    ],
    "基本信息": {
        "性别": [
            "4",
            [
                "男"
            ]
        ],
        "年龄": [
            "2",
            [
                25
            ]
        ],
        "总工作年限": [
            "2",
            [
                1.0
            ]
        ],
        "期望城市": [
            "4",
            [
                "上海"
            ]
        ]
    },
    "其他标签": []
}