{
    "basic": {
        "birthday": "1992-01",
        "currentCity": "西安-碑林区",
        "gender": "男",
        "nationality": "中国",
        "registeredResidence": "定西"
    },
    "confidentialResume": "N",
    "currentCompany": "上海斐讯数据通信技术有限公司",
    "currentIndustry": "计算机硬件/网络设备",
    "currentPosition": "销售经理",
    "degree": "本科",
    "eduExp": [
        {
            "degree": "本科",
            "endDate": "2017-06",
            "major": "采矿与岩土工程 辅修工商管理",
            "school": "中南大学",
            "startDate": "2013-09"
        }
    ],
    "idStr": "",
    "jobObjective": {
        "city": "西安;成都",
        "industry": "计算机硬件/网络设备",
        "position": "促销经理/主管;品牌经理/主管;市场拓展经理/主管",
        "salary": "14.00万（10000元/月 * 14个月）"
    },
    "otherLangResumeId": "5b7b7768f0f0970a8a14558a",
    "projectExp": [],
    "selfComm": "\n1.对本行业充满热情，喜欢线上线下的销售，对商业模式有一定的了解，善于整合各种资源进行营销，能使用合适的方法，分析应用策略和盈利模式，善于把握用户心理进行传递品牌产品信息，进行线上线下或粉丝活动策划进行营销推广，品牌营销策划能力强。 \n2.善于沟通，做事积极主动，学习能力强，善于沟通，注重团队合作，良好的组织协调能力，较强的分析能力和创造性解决问题的能力。 \n3.良好的人际交往能力和团队管理能力。丰富的社会实践、社团实践经验充分锻炼了人际交往能力和团队管\n",
    "version": "zh",
    "workExp": [
        {
            "company": "上海斐讯数据通信技术有限公司",
            "detail": "- 所在地区：西安 \n - 汇报对象：西北大区销售总监 \n - 下属人数：0人 \n - 职责业绩： \n1.负责斐讯智能硬件产品、数通产品、路由器、智能家居等系列产品在陕西省市场的销售。维护斐讯在陕西市场现有的手机渠道、运营商渠道、IT渠道等以及其他渠道的省级代理商，促进其斐讯产品的销售。以及挖掘和开拓相应新的市场渠道；\n2.负责省级行业客户的扩展，并且协同渠道进行重要客户群管理;\n3.在省级销售办事处的二个月时间内，不断的陌生拜访未开发的各个行业客户，最后促成知名的 IT \n全国连锁渠道商&ldquo;三叶网络科技有限公司&rdquo;和斐讯签订省级代理商协议，且把斐讯产品作为其年度重点销售产品推向西北五省的市场渠道。后续我不断的帮各个省级代理商维护开拓各个行业客户市场，经过三个月的努力，帮其梳理和建立了完善的市场渠道，且个人月销售业绩从刚开始的 \n0提升到 80万，再从80 万提升到现在的500多万，超两倍完成公司给个人制定的销售任务。\n",
            "endDate": "4000-10",
            "position": "销售经理",
            "startDate": "2017-07"
        },
        {
            "company": "上海万觅网络科技有限公司 （APP名称--全民共享）",
            "detail": "- 所在地区：长沙 \n - 汇报对象：总裁 \n - 下属人数：20人 \n - 职责业绩： \n1.负责前期时间技能共享平台的市场需求分类调查和产品服务方向的定位，以及后期产品的设计和运营。\n2.负责&ldquo;全民共享&rdquo;APP的的上线和运营工作。在线上转发微信软文，传播到各个学院的求职招聘群，引导同学下载APP并参加活动，提高推广覆盖度。且招募校园大使，寻找hr，让hr参加我们的&ldquo;hr带你玩转招聘会&rdquo;，提高活动形象和名气\n3.利用资源整合能力，几乎&ldquo;0成本&rdquo;策划发起&ldquo;长沙大学生陌生人亲吻&rdquo;活动。并邀约媒体进行跟踪采访，使得其新闻登录各大新闻网站头条。加上后来天津日报采访的正面澄清新闻，后经反复&ldquo;炒作&rdquo;，使得新组建的创业团队以及初期的产品名称走进了相应市场需求人群的视野，打响了名号，起到了良好的宣传效果。\n",
            "endDate": "2017-02",
            "position": "联合创始人（产品和运营）",
            "startDate": "2016-07"
        }
    ],
    "workYears": 2.0
}