{
    "basic": {
        "birthday": "1986-6-8",
        "currentCity": "陕西省",
        "gender": "男",
        "maritalStatus": "已婚",
        "photoAddress": "http://img01.51jobcdn.com/im/2016/resume/man.png",
        "politicalStatus": "共青团员",
        "registeredResidence": "延安",
        "zipCode": "716000"
    },
    "certificate": " \n2008/7 大学英语四级 ",
    "confidentialResume": "N",
    "currentCompany": "惠氏公司",
    "currentIndustry": "医疗/保健/美容/卫生服务",
    "currentPosition": "销售经理",
    "currentSalary": "",
    "degree": "本科",
    "eduExp": [
        {
            "degree": "本科",
            "detail": "\n市场营销、网络营销、市场调查与预测、经济学、基础会计、国际贸易、电子商务、企业管理、电子商务法、电子商务解决方案、c+,VB程序设计、VF数据库、ERP企业资源管理、SQL \nServer2000数据库、进出口业务与报关、商务英语等。",
            "endDate": "2010-09",
            "major": "电子商务",
            "school": "西北农林科技大学",
            "startDate": "2006-07"
        }
    ],
    "idStr": "",
    "jobObjective": {
        "city": "陕西省",
        "contractTerm": "全职",
        "industry": "快速消费品(食品、饮料、化妆品),制药/生物工程",
        "position": "销售经理,销售经理",
        "salary": "20000-24999 元/月 ",
        "state": "目前正在找工作\n到岗时间：1周内"
    },
    "langAbility": " \n英语 良好 ",
    "otherLangResumeId": "5c30d8d9f0f096e7c8220f25",
    "otherLangResumeSite": "51job.com",
    "otherSourceId": "96329244",
    "projectExp": [],
    "selfComm": "1工作背景：多年销售管理经验，多次带领团队超额完成业绩目标\n2专业能力：敏锐快捷的市场反应能力和实战能力；良好的人际交往及客户关系维护能力；良好的工作计划能力、沟通协调能力、数据分析能力及整体结构性思维。 \n3领导能力：丰富的团队管理经验，善于团结、带领队伍达成工作目标，较强的执行力及开拓力。 \n4性格品质：脚踏实地、高度敬业、善于沟通、处事圆融、敢于担当、正直果敢。 \n5兴趣爱好：爱好阅读、旅行，进而开阔视野等，注重个人综合素质的培养和提升。 \n6服务理念：传递正能量，让人们生活的更美好。",
    "version": "zh",
    "workExp": [
        {
            "company": "惠氏(中国)公司",
            "department": "销售部",
            "detail": "1业务管理：以业绩目标为核心，通过各环节把控，超额完成组织绩效，为企业做到利益最大化。 \n2团队管理：通过激励、培养、团队打造等，为团队赋能，同时推动员工成长及组织绩效达成。 \n3客户管理：从客户开发及关系维护两方面，做好客户管理，提升公司品牌，为目标业绩完成蓄力。 \n4品牌营销：前期的项目谈判对接，培训筹划、过往数据分析及目标额制定；执行中的协调及统筹，全面权衡确保营销推广活动顺利进行；活动后的数据各维度分析（销售额、预约数据、环比同比增长等），分析现状及原因，进行复盘），最终活动结案报告的体现。\n5招标支持：分析竞品及自我优势；标书制作；客户谈判等完成招标事宜。",
            "endDate": "4000-10",
            "industry": "制药/生物工程",
            "position": "销售经理",
            "scale": "5000-10000人",
            "startDate": "2014-10",
            "type": "外资(欧美)"
        },
        {
            "company": "白云山药业品牌部",
            "department": "西北大区",
            "detail": "1团队建设：人才体系重构，按照中级业务代表的岗位人才方向，针对性进行高质量人员招聘，确保团队稳定性及目标绩效达成。 \n2业务管理：制定大区重点目标医院OTC业务计划，领导营销团队实现公司的各项销售指标。包含业绩目标拆分，过程管控，数据分析报告等。 \n3活动策划：线下活动统筹，基于会员数据、销售额，品牌影响力等数据分析。制定合适的品牌营销方案及落地执行。 \n4资源维护：确定重点目标医院OTC渠道的关键决策人，建立良好关系，通过和相关医院协会，药协会的合作，为公司和重点目标医院KDM之间建立高效信息沟通桥梁。医院各科室关系维护，课件制作，学术会议推广；规范市场运作流程，分析可控目标，协助OTC客户完成目标，做好维护跟进。",
            "endDate": "2014-09",
            "industry": "制药/生物工程",
            "position": "DSM",
            "scale": "10000人以上",
            "startDate": "2009-11",
            "type": "国企"
        }
    ],
    "workYears": 11.0
}