{
    "in_path": "D:/Project/NER_Interface_v3_20190412/ner_interface/data/CV_Origin_Data/201808-119383SrAccountExecutive/586d6dd4f0f0117de8b68b51.json",
    "id": "586d6dd4f0f0117de8b68b51",
    "工作年限": 10.0,
    "工作城市": [
        "西安"
    ],
    "专业": [
        "计算机控制技术（航空电子）"
    ],
    "毕业院校": [
        "西安航空学院"
    ],
    "学历": [
        "大专"
    ],
    "工作经验": [
        {
            "工作公司": "海克斯康测量技术（青岛）有限公司",
            "公司规模": "500-1000人",
            "工作行业": [
                "电子技术",
                "半导体",
                "集成电路"
            ],
            "工作部门": [
                "商务部"
            ],
            "工作职位": [
                "产品工程师"
            ],
            "岗位工作年限": 2.0,
            "工作描述": {
                "技能": [
                    "影像测量",
                    "测量硬件光学部件选型测试",
                    "自动测量编程",
                    "客户培训",
                    "客户产品调研"
                ],
                "学历": [],
                "专业": [],
                "行业": [],
                "职能": [],
                "年限": [],
                "业务": [
                    "光学测量",
                    "海克斯",
                    "光学校正",
                    "测量精度补偿",
                    "光学镜头测试选型",
                    "光学测量传感器",
                    "产品管理"
                ],
                "产品": []
            }
        },
        {
            "工作公司": "康代Camtek影像科技(苏州)有限公司",
            "公司规模": "150-500人",
            "工作行业": [
                "电子技术",
                "半导体",
                "集成电路"
            ],
            "工作部门": [
                "售后服务部"
            ],
            "工作职位": [
                "售前",
                "售后技术支持工程师"
            ],
            "岗位工作年限": 5.9,
            "工作描述": {
                "技能": [
                    "光学影像设备",
                    "自动光学检测硬件软件",
                    "客户培训",
                    "计算机硬件",
                    "软体系统",
                    "TCP",
                    "IP协议",
                    "网络知识",
                    "绿油防焊",
                    "白字字符",
                    "新技术"
                ],
                "学历": [],
                "专业": [],
                "行业": [],
                "职能": [],
                "年限": [],
                "业务": [
                    "自动光学检测原理",
                    "光学校正设定",
                    "光学检测",
                    "AOI算法"
                ],
                "产品": []
            }
        },
        {
            "工作公司": "意法半导体（深圳）有限公司",
            "公司规模": "500-1000人",
            "工作行业": [
                "电子技术",
                "半导体",
                "集成电路"
            ],
            "工作部门": [
                "FLIPCHIP"
            ],
            "工作职位": [
                "设备工程师"
            ],
            "岗位工作年限": 2.9,
            "工作描述": {
                "技能": [
                    "Flipchip",
                    "Bumping",
                    "laser",
                    "marking",
                    "die",
                    "sawing",
                    "工艺流程",
                    "设备技术原理",
                    "倒装芯片Assembly",
                    "微波发生器",
                    "Die",
                    "Saw机器工作原理",
                    "调试",
                    "设备原理",
                    "调试",
                    "机型",
                    "美国AU"
                ],
                "学历": [],
                "专业": [],
                "行业": [],
                "职能": [],
                "年限": [],
                "业务": [
                    "SAW 机器",
                    "维护"
                ],
                "产品": []
            }
        }
    ],
    "项目经验": [
        {
            "项目名称": "康代3D喷墨设备客户端评估",
            "项目时长": 0.8,
            "项目描述": {
                "技能": [
                    "评"
                ],
                "学历": [],
                "专业": [],
                "行业": [],
                "职能": [],
                "年限": [],
                "业务": [],
                "产品": []
            }
        },
        {
            "项目名称": "康代AOI升级",
            "项目时长": 0.5,
            "项目描述": {
                "技能": [
                    "Dragon系列软件",
                    "Phoenix软件",
                    "侦测能力"
                ],
                "学历": [],
                "专业": [],
                "行业": [],
                "职能": [],
                "年限": [],
                "业务": [],
                "产品": []
            }
        }
    ],
    "技能": [
        "康代年度优秀员工",
        "中级工程师",
        "大学英语四级"
    ],
    "语言": {
        "英语": "良好"
    },
    "自我评价": {
        "技能": [
            "团队意识",
            "沟通能力"
        ],
        "学历": [],
        "专业": [],
        "行业": [],
        "职能": [],
        "年限": [],
        "业务": [],
        "产品": []
    },
    "业务": "",
    "产品": ""
}