{
    "in_path": "D:/Project/NER_Interface_v3_20190412/ner_interface/data/CV_Origin_Data/201808-119383SrAccountExecutive/58ab1145b1220535d76c2122.json",
    "id": "58ab1145b1220535d76c2122",
    "工作年限": 8.0,
    "工作城市": [
        "陕西省"
    ],
    "专业": [
        "药学"
    ],
    "毕业院校": [
        "陕西中医药大学"
    ],
    "学历": [
        "本科"
    ],
    "工作经验": [
        {
            "工作公司": "德赛诊断系统（上海）有限公司",
            "公司规模": "50-150人",
            "工作行业": [
                "医疗设备",
                "器械"
            ],
            "工作部门": [
                "销售部"
            ],
            "工作职位": [
                "销售经理"
            ],
            "岗位工作年限": 1.4,
            "工作描述": {
                "技能": [],
                "学历": [
                    "汉"
                ],
                "专业": [],
                "行业": [],
                "职能": [],
                "年限": [
                    "8",
                    "7"
                ],
                "业务": [
                    "小型生化仪销售",
                    "陕",
                    "西",
                    "第",
                    "汉",
                    "安",
                    "宝",
                    "榆",
                    "榆",
                    "韩",
                    "销",
                    "生",
                    "免",
                    "床"
                ],
                "产品": []
            }
        },
        {
            "工作公司": "基蛋生物科技股份有限公司",
            "公司规模": "1000-5000人",
            "工作行业": [
                "医疗设备",
                "器械"
            ],
            "工作部门": [
                "销售部"
            ],
            "工作职位": [
                "医疗器械销售经理",
                "主管"
            ],
            "岗位工作年限": 1.3,
            "工作描述": {
                "技能": [
                    "医疗器械",
                    "经销商",
                    "poct"
                ],
                "学历": [],
                "专业": [],
                "行业": [],
                "职能": [],
                "年限": [],
                "业务": [
                    "诊断试剂",
                    "三级",
                    "医疗设备",
                    "器械"
                ],
                "产品": []
            }
        },
        {
            "工作公司": "哈药集团",
            "公司规模": "500-1000人",
            "工作行业": [
                "制药",
                "生物工程"
            ],
            "工作部门": [
                "营销公司"
            ],
            "工作职位": [
                "销售主管"
            ],
            "岗位工作年限": 4.9,
            "工作描述": {
                "技能": [
                    "商务",
                    "区域控销市场",
                    "商务分销",
                    "控销市场",
                    "渠道管理",
                    "西安商业渠道商务",
                    "分销业务"
                ],
                "学历": [],
                "专业": [],
                "行业": [
                    "医药行业",
                    "商业"
                ],
                "职能": [],
                "年限": [
                    "5年",
                    "5年"
                ],
                "业务": [
                    "分销渠道",
                    "发货",
                    "市场维护",
                    "销售",
                    "机会施展"
                ],
                "产品": []
            }
        }
    ],
    "项目经验": [
        {
            "项目名称": "咸阳市场销售",
            "项目时长": 2.8,
            "项目描述": {
                "技能": [],
                "学历": [],
                "专业": [],
                "行业": [],
                "职能": [],
                "年限": [
                    "一年"
                ],
                "业务": [],
                "产品": []
            }
        }
    ],
    "技能": [
        "药师证",
        "医药购销员证",
        "计算机中级"
    ],
    "语言": {
        "英语": "良好"
    },
    "自我评价": {
        "技能": [
            "经销商",
            "维护终端客户",
            "渠道管理",
            "西安商业渠道商务",
            "分销业务",
            "9-2010"
        ],
        "学历": [],
        "专业": [],
        "行业": [],
        "职能": [],
        "年限": [
            "5年",
            "2年"
        ],
        "业务": [
            "开发新客户",
            "机会施展"
        ],
        "产品": []
    },
    "业务": "",
    "产品": ""
}