{
    "in_path": "D:/Project/NER_Interface_v3_20190412/ner_interface/data/CV_Origin_Data/201808-119383SrAccountExecutive/5a141bdaf0f06161ee0b0cf9.json",
    "id": "5a141bdaf0f06161ee0b0cf9",
    "工作年限": 9.0,
    "工作城市": [
        "郑州",
        "西安",
        "成都"
    ],
    "专业": [
        "国际经济与贸易"
    ],
    "毕业院校": [
        "西北民族大学"
    ],
    "学历": [
        "本科"
    ],
    "工作经验": [
        {
            "工作公司": "广州吉七信息有限公司G7",
            "工作职位": [
                "西北区域总监"
            ],
            "岗位工作年限": 0.6,
            "工作描述": {
                "技能": [
                    "组织架构"
                ],
                "学历": [],
                "专业": [],
                "行业": [],
                "职能": [],
                "年限": [],
                "业务": [
                    "系统分析",
                    "市场现状进行调研"
                ],
                "产品": []
            }
        },
        {
            "工作公司": "西安顺丰速运有限公司",
            "工作职位": [
                "片区负责人"
            ],
            "岗位工作年限": 1.1,
            "工作描述": {
                "技能": [
                    "汇报对象"
                ],
                "学历": [],
                "专业": [],
                "行业": [],
                "职能": [],
                "年限": [],
                "业务": [
                    "管理",
                    "大客户开发",
                    "跟进",
                    "运营维护",
                    "片区创新项目的开发",
                    "拓展"
                ],
                "产品": []
            }
        },
        {
            "工作公司": "深圳市毅德投资管理有限公司",
            "工作职位": [
                "营销总监"
            ],
            "岗位工作年限": 7.3,
            "工作描述": {
                "技能": [
                    "规划设计",
                    "管理制度",
                    "销售计划",
                    "预算",
                    "监督执行计划",
                    "重点客户攻关",
                    "谈判"
                ],
                "学历": [],
                "专业": [],
                "行业": [],
                "职能": [],
                "年限": [
                    "-"
                ],
                "业务": [
                    "销售任务",
                    "兰州项目",
                    "推广策略",
                    "调研报告制定业态规划",
                    "定位",
                    "日常管理"
                ],
                "产品": []
            }
        },
        {
            "工作公司": "中铁隧道勘查设计院西安项目部",
            "工作职位": [
                "测量测绘"
            ],
            "岗位工作年限": 0.8,
            "工作描述": {
                "技能": [],
                "学历": [],
                "专业": [],
                "行业": [],
                "职能": [],
                "年限": [],
                "业务": [
                    "人数:0人 ",
                    "西安地铁一二号线"
                ],
                "产品": []
            }
        }
    ],
    "项目经验": [
        {
            "项目名称": "深圳毅德投资管理有限公司柳州项目",
            "项目时长": 0.7,
            "项目描述": {
                "技能": [
                    "招商计划",
                    "策略制定",
                    "营销策划"
                ],
                "学历": [],
                "专业": [],
                "行业": [
                    "商业",
                    "仓储",
                    "物流"
                ],
                "职能": [],
                "年限": [
                    " -",
                    "8年年",
                    " -"
                ],
                "业务": [
                    "招商总监 ",
                    "销售商业",
                    "销售管理",
                    "销售说辞撰写",
                    "培训和管理",
                    "大客户谈判",
                    "定位拟定"
                ],
                "产品": []
            }
        },
        {
            "项目名称": "深圳毅德投资管理有限公司烟台项目",
            "项目时长": 0.5,
            "项目描述": {
                "技能": [
                    "由毅德控股投资开发"
                ],
                "学历": [],
                "专业": [],
                "行业": [
                    "国际商贸城",
                    "物流"
                ],
                "职能": [],
                "年限": [
                    " -"
                ],
                "业务": [
                    ":营销总监 ",
                    "集散地",
                    "本人接管项目",
                    "前期开盘销售",
                    "后期持续销售",
                    "带项目组接管",
                    "培训团队",
                    "销售"
                ],
                "产品": []
            }
        },
        {
            "项目名称": "深圳毅德投资管理有限公司兰州项目",
            "项目时长": 0.3,
            "项目描述": {
                "技能": [
                    "汽摩配",
                    "电子商务",
                    "商业综合体",
                    "星级酒店",
                    "会展中心",
                    "智能化仓储物流",
                    "现代化程度最高",
                    "交易门类最全",
                    "服务最完善",
                    "辐射能力",
                    "年度销售计划",
                    "回款计划",
                    "规划同时"
                ],
                "学历": [],
                "专业": [
                    "家具家居"
                ],
                "行业": [
                    "商贸城",
                    "协调公司"
                ],
                "职能": [],
                "年限": [
                    " -"
                ],
                "业务": [
                    ":营销总监 ",
                    "陶瓷建材",
                    "五金机电",
                    "金融服务",
                    "休闲娱乐",
                    "商贸交易",
                    "城市规模最大",
                    "人民币",
                    "营销推广方案",
                    "市场商户进驻",
                    "项目组接管",
                    "市场深耕"
                ],
                "产品": []
            }
        },
        {
            "项目名称": "浙商国际商贸城",
            "项目时长": 0.8,
            "项目描述": {
                "技能": [
                    "营销推广方案",
                    "营销队伍管理"
                ],
                "学历": [],
                "专业": [],
                "行业": [],
                "职能": [],
                "年限": [],
                "业务": [
                    ":营销总监 ",
                    "开发建设",
                    "浙商国际商贸城项目",
                    "五金机电交易",
                    "五金装饰装潢交易",
                    "大型批发市场市场",
                    "市场调研制定业态定位",
                    "规划",
                    "营销策划方案",
                    "制定项目销售价",
                    "销售",
                    "策划"
                ],
                "产品": []
            }
        },
        {
            "项目名称": "靖西云天城",
            "项目时长": 1.6,
            "项目描述": {
                "技能": [
                    "规划设计",
                    "组织团队制定"
                ],
                "学历": [],
                "专业": [],
                "行业": [],
                "职能": [],
                "年限": [
                    " -"
                ],
                "业务": [
                    ":营销总监 ",
                    "跨境商贸产业地产运营商",
                    "城镇化发展",
                    "商贸交易平台",
                    "桂西商贸第一城",
                    "商",
                    "都",
                    "五",
                    "组建队伍",
                    "打造项目招商",
                    "销售",
                    "业务技能培训",
                    "企业文化培训",
                    "市场调研",
                    "营销方案",
                    "人力推广",
                    "渠道铺设",
                    "销售750"
                ],
                "产品": []
            }
        }
    ],
    "自我评价": {
        "技能": [
            "执行力&#",
            "凝聚外力",
            "外脑才能"
        ],
        "学历": [],
        "专业": [],
        "行业": [],
        "职能": [],
        "年限": [],
        "业务": [
            "人人互助"
        ],
        "产品": []
    },
    "业务": "",
    "产品": ""
}