{
    "in_path": "D:/Project/NER_Interface_v3_20190412/ner_interface/data/CV_Origin_Data/201808-119383SrAccountExecutive/5b63a93ef0f0c84c3d8d4934.json",
    "id": "5b63a93ef0f0c84c3d8d4934",
    "工作年限": 10.0,
    "工作城市": [
        "北京",
        "西安"
    ],
    "专业": [
        "预防兽医"
    ],
    "毕业院校": [
        "中国农业科学院"
    ],
    "学历": [
        "硕士"
    ],
    "工作经验": [
        {
            "工作公司": "正大种猪场",
            "工作职位": [
                "种猪场兽医"
            ],
            "岗位工作年限": 1.3,
            "工作描述": {
                "技能": [],
                "学历": [],
                "专业": [],
                "行业": [],
                "职能": [],
                "年限": [
                    "-"
                ],
                "业务": [
                    "人数:0人 ",
                    "物安全系统",
                    "传染病诊断",
                    "猪群健康管理"
                ],
                "产品": []
            }
        },
        {
            "工作公司": "嘉吉普瑞纳 华威特生物制药",
            "工作职位": [
                "研发 技术服务"
            ],
            "岗位工作年限": 1.8,
            "工作描述": {
                "技能": [
                    "研究生课题"
                ],
                "学历": [
                    "硕士"
                ],
                "专业": [],
                "行业": [],
                "职能": [],
                "年限": [
                    "-"
                ],
                "业务": [
                    "人数:0人 ",
                    "传染病预防诊断",
                    "疫苗产品制作规程"
                ],
                "产品": []
            }
        },
        {
            "工作公司": "嘉吉普瑞纳品牌",
            "工作职位": [
                "technical service ，sales manger"
            ],
            "岗位工作年限": 4.3,
            "工作描述": {
                "技能": [
                    "规模猪场南通",
                    "用户会议",
                    "经销商会议",
                    "病毒性",
                    "细菌性疾病病理",
                    "防控方法",
                    "改善方案",
                    "猪场生产管理",
                    "细菌性疾病防控"
                ],
                "学历": [],
                "专业": [],
                "行业": [],
                "职能": [],
                "年限": [
                    "-",
                    "三年",
                    "三年"
                ],
                "业务": [
                    "人数:0人 ",
                    "猪场提供环境管理",
                    "产房管理",
                    "饲养管理",
                    "猪场设计",
                    "市场活动",
                    "猪场设计",
                    "批次管理",
                    "产房管理",
                    "饲养管理"
                ],
                "产品": []
            }
        }
    ],
    "项目经验": [
        {
            "项目名称": "动物重大传染病疫苗及诊断试剂研制",
            "项目时长": 2.0,
            "项目描述": {
                "技能": [
                    "IBR疫苗研制"
                ],
                "学历": [],
                "专业": [],
                "行业": [],
                "职能": [],
                "年限": [],
                "业务": [
                    "项目职务:项目经理 ",
                    "诊断试剂"
                ],
                "产品": []
            }
        }
    ],
    "自我评价": {
        "技能": [],
        "学历": [],
        "专业": [],
        "行业": [],
        "职能": [],
        "年限": [],
        "业务": [],
        "产品": []
    },
    "业务": "",
    "产品": ""
}