{
    "in_path": "D:/Project/NER_Interface_v3_20190412/ner_interface/data/CV_Origin_Data/201804-101824ApplicationsSpecialist/5b8f428cf0f03e8b31a1348a.json",
    "id": "5b8f428cf0f03e8b31a1348a",
    "工作年限": "",
    "工作城市": [
        "厦门"
    ],
    "专业": [
        "电子工程与自动化"
    ],
    "毕业院校": [
        "安庆电子技校"
    ],
    "学历": [
        "中技"
    ],
    "工作经验": [
        {
            "工作公司": "厦门金三木机电",
            "工作职位": [
                "电子",
                "电器维修工程师",
                "技师"
            ],
            "岗位工作年限": 12.0,
            "工作描述": {
                "技能": [
                    "医疗设备",
                    "控制电子板维修"
                ],
                "学历": [],
                "专业": [],
                "行业": [],
                "职能": [],
                "年限": [
                    "-"
                ],
                "业务": [],
                "产品": []
            }
        }
    ],
    "自我评价": {
        "技能": [],
        "学历": [],
        "专业": [],
        "行业": [],
        "职能": [],
        "年限": [],
        "业务": [],
        "产品": []
    },
    "业务": "",
    "产品": ""
}