{
    "in_path": "D:/Project/NER_Interface_v3_20190412/ner_interface/data/CV_Origin_Data/201808-119383SrAccountExecutive/5c05ffd26670d4c8bcc85187.json",
    "id": "5c05ffd26670d4c8bcc85187",
    "工作年限": 7.0,
    "工作城市": [
        "西安"
    ],
    "专业": [
        "生物工程"
    ],
    "毕业院校": [
        "西北大学"
    ],
    "学历": [
        "本科"
    ],
    "工作经验": [
        {
            "工作公司": "贝朗医疗(上海)国际贸易有限公司",
            "工作部门": [
                "安全输液"
            ],
            "工作职位": [
                "销售"
            ],
            "岗位工作年限": 2.5,
            "工作描述": {
                "技能": [
                    "自主开发"
                ],
                "学历": [],
                "专业": [],
                "行业": [],
                "职能": [],
                "年限": [],
                "业务": [
                    "市场渠道开拓与销售",
                    "销售计划",
                    "开拓新",
                    "销售",
                    "新客户"
                ],
                "产品": []
            }
        },
        {
            "工作公司": "雅培贸易(上海)有限公司",
            "工作部门": [
                "ADC"
            ],
            "工作职位": [
                "销售代表"
            ],
            "岗位工作年限": 2.8,
            "工作描述": {
                "技能": [
                    "管理",
                    "销售报表"
                ],
                "学历": [],
                "专业": [],
                "行业": [
                    "商业公司",
                    "管理"
                ],
                "职能": [],
                "年限": [
                    "一年",
                    "4年"
                ],
                "业务": [
                    "新客户资料",
                    "维护客户关系",
                    "组织推广活动",
                    "销售指标",
                    "销售员工"
                ],
                "产品": []
            }
        },
        {
            "工作公司": "华瑞制药",
            "工作部门": [
                "肠外营养事业部"
            ],
            "工作职位": [
                "医药代表"
            ],
            "岗位工作年限": 1.4,
            "工作描述": {
                "技能": [
                    "客户档案"
                ],
                "学历": [],
                "专业": [
                    "组织产品科室推广会"
                ],
                "行业": [],
                "职能": [],
                "年限": [],
                "业务": [
                    "制订医院拜访计划",
                    "每月保证拜访规定数量",
                    "销售活动",
                    "销售目标",
                    "目标医生",
                    "医院开发",
                    "规定合理",
                    "报告系统",
                    "商业代表",
                    "反馈市场信息",
                    "招标",
                    "配合大区",
                    "地区经理",
                    "销售主管"
                ],
                "产品": []
            }
        },
        {
            "工作公司": "步长集团",
            "工作部门": [
                "事业特部"
            ],
            "工作职位": [
                "医药代表"
            ],
            "岗位工作年限": 1.0,
            "工作描述": {
                "技能": [
                    "组织参",
                    "客户升级"
                ],
                "学历": [],
                "专业": [],
                "行业": [],
                "职能": [],
                "年限": [],
                "业务": [
                    "销售任务",
                    "科会",
                    "开发医院",
                    "科室"
                ],
                "产品": []
            }
        }
    ],
    "项目经验": [
        {
            "项目名称": "低成本的环保型聚乳酸类包装材料的关键技术研究",
            "项目时长": 1.7,
            "项目描述": {
                "技能": [],
                "学历": [],
                "专业": [],
                "行业": [],
                "职能": [],
                "年限": [],
                "业务": [
                    "项目业绩:"
                ],
                "产品": []
            }
        }
    ],
    "语言": {
        "英语,普通话": ""
    },
    "自我评价": {
        "技能": [
            "表达能力",
            "适应能力"
        ],
        "学历": [],
        "专业": [],
        "行业": [],
        "职能": [],
        "年限": [],
        "业务": [],
        "产品": []
    },
    "业务": "",
    "产品": ""
}