{
    "in_path": "D:/Project/NER_Interface_v3_20190412/ner_interface/data/CV_Origin_Data/201808-119383SrAccountExecutive/5c174e87f0f059a23ea666d0.json",
    "id": "5c174e87f0f059a23ea666d0",
    "工作年限": 13.0,
    "工作城市": [
        "西安"
    ],
    "专业": [
        "临床医学",
        "临床医学与医学技术"
    ],
    "毕业院校": [
        "西安交通大学",
        "延安大学"
    ],
    "学历": [
        "本科",
        "大专"
    ],
    "工作经验": [
        {
            "工作公司": "某医疗器械集团有限公司",
            "工作职位": [
                "集团业务总监"
            ],
            "岗位工作年限": 2.7,
            "工作描述": {
                "技能": [
                    "副总经理"
                ],
                "学历": [
                    "骨科"
                ],
                "专业": [],
                "行业": [],
                "职能": [],
                "年限": [
                    "-"
                ],
                "业务": [
                    "组",
                    "投入运营",
                    "业务运营管理"
                ],
                "产品": []
            }
        },
        {
            "工作公司": "某控股医疗器械有限公司",
            "工作职位": [
                "全国销售业务经理"
            ],
            "岗位工作年限": 2.8,
            "工作描述": {
                "技能": [
                    "副总经理"
                ],
                "学历": [],
                "专业": [],
                "行业": [],
                "职能": [],
                "年限": [
                    "-"
                ],
                "业务": [
                    "骨科",
                    "工具管理",
                    "仓库管理",
                    "采购管理",
                    "分库建设",
                    "投入运营"
                ],
                "产品": []
            }
        },
        {
            "工作公司": "联贸医疗用品技术(上海)有限公司",
            "工作职位": [
                "市场专员"
            ],
            "岗位工作年限": 0.9,
            "工作描述": {
                "技能": [],
                "学历": [
                    "骨科",
                    "骨科展会"
                ],
                "专业": [],
                "行业": [],
                "职能": [],
                "年限": [
                    "-"
                ],
                "业务": [
                    "人数:0人 ",
                    " 台湾联合髋膝系列产品",
                    "产品培训",
                    "代理商培训",
                    "医院",
                    "新开发医院",
                    "推广会议",
                    "新业务开展培训12 ",
                    "代理商业务培训"
                ],
                "产品": []
            }
        },
        {
            "工作公司": "上海铭耀医疗器械有限公司",
            "工作职位": [
                "销售经理"
            ],
            "岗位工作年限": 4.5,
            "工作描述": {
                "技能": [
                    "smith",
                    "nephew",
                    "DePuy"
                ],
                "学历": [
                    "骨科"
                ],
                "专业": [],
                "行业": [],
                "职能": [],
                "年限": [
                    "-"
                ],
                "业务": [
                    "销售",
                    "后期",
                    "进口创伤产品",
                    "销售美国施乐",
                    "品牌产品",
                    "物产品",
                    "骨科创伤产品",
                    "跟进",
                    "反馈",
                    "仓库",
                    "跟台人员",
                    "培训",
                    "产品销量"
                ],
                "产品": []
            }
        },
        {
            "工作公司": "宁波医疗器械有限公司",
            "工作职位": [
                "销售代表"
            ],
            "岗位工作年限": 2.0,
            "工作描述": {
                "技能": [
                    "跟台技术"
                ],
                "学历": [
                    "骨科"
                ],
                "专业": [],
                "行业": [],
                "职能": [],
                "年限": [
                    "-"
                ],
                "业务": [
                    "人数:0人 ",
                    "销售产品"
                ],
                "产品": []
            }
        }
    ],
    "项目经验": [
        {
            "项目名称": "骨科内植物供应链管理平台建设",
            "项目时长": 2.5,
            "项目描述": {
                "技能": [],
                "学历": [],
                "专业": [],
                "行业": [
                    "仓储物流"
                ],
                "职能": [],
                "年限": [
                    " -"
                ],
                "业务": [
                    ":业务总监 ",
                    "仓储物流平台建设",
                    "分库建设",
                    "投入运营",
                    "投入运营",
                    "业务运营管理"
                ],
                "产品": []
            }
        }
    ],
    "自我评价": {
        "技能": [
            "沟通",
            "团队协作能力"
        ],
        "学历": [
            "骨科",
            "骨科"
        ],
        "专业": [],
        "行业": [],
        "职能": [
            "管理"
        ],
        "年限": [
            "1",
            "3年",
            "5年"
        ],
        "业务": [
            "骨科全线产品销售",
            "代理商市场",
            "骨科供应链平台建设",
            "运营管理",
            "团队建设与管理"
        ],
        "产品": []
    },
    "业务": "",
    "产品": ""
}