{
    "in_path": "D:/Project/NER_Interface_v3_20190412/ner_interface/data/CV_Origin_Data/201808-119383SrAccountExecutive/5c21dd63f0f0ed7cb6cffe95.json",
    "id": "5c21dd63f0f0ed7cb6cffe95",
    "工作年限": 11.0,
    "工作城市": [
        "西安"
    ],
    "专业": [
        "工商管理"
    ],
    "毕业院校": [
        "西北大学"
    ],
    "学历": [
        "本科"
    ],
    "工作经验": [
        {
            "工作公司": "陕西中烟工业有限责任公司",
            "工作职位": [
                "销售经理"
            ],
            "岗位工作年限": 5.5,
            "工作描述": {
                "技能": [
                    "市场营销"
                ],
                "学历": [],
                "专业": [],
                "行业": [],
                "职能": [],
                "年限": [
                    "-",
                    "2年",
                    "5年"
                ],
                "业务": [
                    "零售户开展拜访",
                    "客情维护",
                    "团购婚庆",
                    "市场销量",
                    "业务拓展",
                    "新品引入开发地市",
                    "销售活动",
                    "廊坊",
                    "市销售"
                ],
                "产品": []
            }
        },
        {
            "工作公司": "华龙证券",
            "工作职位": [
                "区域经理"
            ],
            "岗位工作年限": 2.0,
            "工作描述": {
                "技能": [
                    "组建营销体系网络",
                    "产品营销"
                ],
                "学历": [],
                "专业": [],
                "行业": [
                    "融资融券业务"
                ],
                "职能": [],
                "年限": [
                    "-"
                ],
                "业务": [
                    "网点洽谈",
                    "维护银行客户",
                    "数量化产品",
                    "创新产品",
                    "集合理财",
                    "保持联系维护",
                    "销售团队",
                    "培训",
                    "银行渠道的开拓",
                    "渠道开发",
                    "投资咨询",
                    "股权托管",
                    "三板业务",
                    "资产管理规模"
                ],
                "产品": []
            }
        },
        {
            "工作公司": "中国中投证券有限责任公司",
            "工作职位": [
                "区域经理"
            ],
            "岗位工作年限": 2.2,
            "工作描述": {
                "技能": [],
                "学历": [],
                "专业": [],
                "行业": [],
                "职能": [],
                "年限": [
                    "-"
                ],
                "业务": [
                    "金融渠道维护",
                    "开拓工作",
                    "培训",
                    "组织多次营销活动",
                    "营销制度的制定与营销队伍",
                    "策划营销服务活动",
                    "任务指标",
                    "产品销售",
                    "维护银行网点渠道",
                    "客户经理",
                    "驻点销售",
                    "培训"
                ],
                "产品": []
            }
        },
        {
            "工作公司": "华泰证券股份有限公司",
            "工作职位": [
                "客户经理"
            ],
            "岗位工作年限": 2.0,
            "工作描述": {
                "技能": [
                    "股票开户基金",
                    "投资咨询"
                ],
                "学历": [],
                "专业": [],
                "行业": [],
                "职能": [],
                "年限": [
                    "-",
                    "7年"
                ],
                "业务": [
                    "人数:0人 ",
                    "股票证券开户",
                    "拓展市场",
                    "投资咨询"
                ],
                "产品": []
            }
        }
    ],
    "自我评价": {
        "技能": [],
        "学历": [],
        "专业": [],
        "行业": [],
        "职能": [],
        "年限": [],
        "业务": [],
        "产品": []
    },
    "业务": "",
    "产品": ""
}