{
    "in_path": "D:/Project/NER_Interface_v3_20190412/ner_interface/data/CV_Origin_Data/201808-119383SrAccountExecutive/5c51372bf0f0531757ccf1c9.json",
    "id": "5c51372bf0f0531757ccf1c9",
    "工作年限": 13.0,
    "工作城市": [
        "陕西"
    ],
    "专业": [
        "生物工程"
    ],
    "毕业院校": [
        "陕西理工学院"
    ],
    "学历": [
        "本科"
    ],
    "工作经验": [
        {
            "工作公司": "天津宽达水产食品有限公司",
            "工作职位": [
                "销售经理"
            ],
            "岗位工作年限": 3.5,
            "工作描述": {
                "技能": [
                    "营销计划",
                    "分解销售目标",
                    "业务谈判",
                    "客户反馈"
                ],
                "学历": [],
                "专业": [],
                "行业": [],
                "职能": [],
                "年限": [
                    "-"
                ],
                "业务": [
                    "市场营销策略",
                    "营销策略",
                    "区域市场开拓",
                    "策划",
                    "业",
                    "评价并协助制定",
                    "培训",
                    "指导",
                    "业务拓展"
                ],
                "产品": []
            }
        },
        {
            "工作公司": "阜丰集团营销公司调味品销售部",
            "工作职位": [
                "陕宁.甘藏青新区域主管"
            ],
            "岗位工作年限": 3.2,
            "工作描述": {
                "技能": [
                    "经销商",
                    "设计销售模式",
                    "客户管理",
                    "财务管理"
                ],
                "学历": [],
                "专业": [],
                "行业": [],
                "职能": [],
                "年限": [
                    "-"
                ],
                "业务": [
                    "分管区域品牌产品",
                    "产品销售渠道建设与管理",
                    "直营客户",
                    "市场预测",
                    "制订销售计划",
                    "销售政策 5",
                    "销售人员招募",
                    "选择",
                    "培训",
                    "调配",
                    "销售业绩考察评估 ",
                    "销售渠道",
                    "防止呆帐坏帐对策",
                    "汇总",
                    "汇报",
                    "提出合理"
                ],
                "产品": []
            }
        },
        {
            "工作公司": "宝鸡阜丰生物科技有限公司",
            "工作职位": [
                "生产部主管、经理"
            ],
            "岗位工作年限": 4.8,
            "工作描述": {
                "技能": [
                    "分配计划",
                    "协调车间",
                    "安全",
                    "基建队",
                    "设备维修队",
                    "质量监督队",
                    "生产技术",
                    "办公室管理",
                    "月底",
                    "原材料",
                    "取样",
                    "送样",
                    "检测",
                    "方面规范化管理"
                ],
                "学历": [
                    "物科"
                ],
                "专业": [],
                "行业": [],
                "职能": [],
                "年限": [
                    "-"
                ],
                "业务": [
                    "200人 ",
                    "制定年度生产计划",
                    "环保",
                    "体系",
                    "生产分厂厂长",
                    "生产技术部经理",
                    "安保科经理",
                    "液碱",
                    "大批的管理",
                    "业务骨干"
                ],
                "产品": []
            }
        }
    ],
    "项目经验": [
        {
            "项目名称": "10万吨谷氨酸钠厂建设",
            "项目时长": 0.5,
            "项目描述": {
                "技能": [
                    "设计",
                    "工艺设计",
                    "设备选型"
                ],
                "学历": [],
                "专业": [],
                "行业": [],
                "职能": [],
                "年限": [
                    " -"
                ],
                "业务": [
                    "项目职务:项目助理 "
                ],
                "产品": []
            }
        }
    ],
    "自我评价": {
        "技能": [],
        "学历": [],
        "专业": [],
        "行业": [],
        "职能": [],
        "年限": [],
        "业务": [],
        "产品": []
    },
    "业务": "",
    "产品": ""
}