{
    "in_path": "D:/Project/NER_Interface_v3_20190412/ner_interface/data/CV_Origin_Data/201808-119383SrAccountExecutive/5c60f697f0f081d2c15d1a6d.json",
    "id": "5c60f697f0f081d2c15d1a6d",
    "工作年限": 7.0,
    "工作城市": [
        "西安"
    ],
    "专业": [
        "机械设计制造及其自动化"
    ],
    "毕业院校": [
        "西安石油大学"
    ],
    "学历": [
        "本科"
    ],
    "工作经验": [
        {
            "工作公司": "三星环新(西安)动力电池有限公司",
            "工作职位": [
                "研发",
                "制造技术"
            ],
            "岗位工作年限": 2.8,
            "工作描述": {
                "技能": [
                    "Cell",
                    "jellroll",
                    "Cell",
                    "部分(集电器)设计",
                    "jellroll",
                    "Cell",
                    "新产品E-Run",
                    "M-Run",
                    "产品设计",
                    "模组技术",
                    "尺寸PPK",
                    "pack",
                    "pack",
                    "模组",
                    "cell",
                    "cell",
                    "分析设备",
                    "扫描电镜",
                    "测定设备",
                    "充放电设备",
                    "cell电化学特性分析",
                    "solidworks",
                    "NX软件"
                ],
                "学历": [],
                "专业": [],
                "行业": [],
                "职能": [],
                "年限": [
                    "-"
                ],
                "业务": [
                    "Cell",
                    "模组研发",
                    "cell",
                    "电器设计",
                    "尺寸进行管理",
                    "设计JIG",
                    "分析问题原因",
                    "产品测试",
                    "三维图纸",
                    "转化二维图纸",
                    "强度分析",
                    "模态分析",
                    "热分析",
                    "振动分析"
                ],
                "产品": []
            }
        },
        {
            "工作公司": "山东科瑞石油装备有限公司",
            "工作职位": [
                "研发工程师"
            ],
            "岗位工作年限": 3.1,
            "工作描述": {
                "技能": [],
                "学历": [],
                "专业": [],
                "行业": [],
                "职能": [],
                "年限": [],
                "业务": [
                    "设计研发",
                    "油管设备",
                    "井口防喷器"
                ],
                "产品": []
            }
        }
    ],
    "自我评价": {
        "技能": [],
        "学历": [],
        "专业": [],
        "行业": [],
        "职能": [],
        "年限": [],
        "业务": [],
        "产品": []
    },
    "业务": "",
    "产品": ""
}