{
    "in_path": "D:/Project/NER_Interface_v3_20190412/ner_interface/data/CV_Origin_Data/201808-119383SrAccountExecutive/5c6e1d2cf0f081041ed3156f.json",
    "id": "5c6e1d2cf0f081041ed3156f",
    "工作年限": 10.0,
    "工作城市": [
        "陕西",
        "西安"
    ],
    "专业": [
        "计算机科学与技术"
    ],
    "毕业院校": [
        "武汉语言文化职业学院"
    ],
    "学历": [
        "大专"
    ],
    "工作经验": [
        {
            "工作公司": "北京麦迪克斯科技有限公司",
            "工作职位": [
                "销售专员"
            ],
            "岗位工作年限": 1.1,
            "工作描述": {
                "技能": [
                    "销售医疗信息化系统及设备",
                    "心肺康复",
                    "影像",
                    "超声",
                    "内镜",
                    "病理",
                    "核医学网络",
                    "全院PACS",
                    "信息化网络系统产品",
                    "心电工作站"
                ],
                "学历": [],
                "专业": [],
                "行业": [],
                "职能": [],
                "年限": [
                    "-"
                ],
                "业务": [
                    "人数:0人 ",
                    "心电电生理网络"
                ],
                "产品": []
            }
        },
        {
            "工作公司": "家居电子商务公司",
            "工作职位": [
                "销售经理"
            ],
            "岗位工作年限": 5.0,
            "工作描述": {
                "技能": [
                    "组建团队",
                    "业务拓展和管理",
                    "制定销售策略"
                ],
                "学历": [],
                "专业": [],
                "行业": [],
                "职能": [],
                "年限": [],
                "业务": [
                    "人数:0人 ",
                    "业务拓展",
                    "渠道分销",
                    "代理商",
                    "维护客户",
                    "活动策划"
                ],
                "产品": []
            }
        },
        {
            "工作公司": "北京五八信息技术有限公司",
            "工作职位": [
                "销售"
            ],
            "岗位工作年限": 2.3,
            "工作描述": {
                "技能": [
                    "制订合理销售方案"
                ],
                "学历": [],
                "专业": [],
                "行业": [],
                "职能": [],
                "年限": [],
                "业务": [
                    "人数:0人 ",
                    "团购业务拓展",
                    "市场动向"
                ],
                "产品": []
            }
        },
        {
            "工作公司": "计算机硬件",
            "工作职位": [
                "销售"
            ],
            "岗位工作年限": 1.4,
            "工作描述": {
                "技能": [
                    "面向全省开发",
                    "产品销售",
                    "建设分销网络"
                ],
                "学历": [],
                "专业": [],
                "行业": [],
                "职能": [],
                "年限": [
                    "-"
                ],
                "业务": [
                    "人数:0人 ",
                    "渠道代理商"
                ],
                "产品": []
            }
        }
    ],
    "自我评价": {
        "技能": [
            "com"
        ],
        "学历": [],
        "专业": [],
        "行业": [],
        "职能": [],
        "年限": [],
        "业务": [
            "招投标整个",
            "销售策略"
        ],
        "产品": []
    },
    "业务": "",
    "产品": ""
}